axioms_flask/__init__.py
axioms_flask/_version.py
axioms_flask/decorators.py
axioms_flask/error.py
axioms_flask/methodview.py
axioms_flask/token.py
axioms_flask_py-0.0.20.dist-info/licenses/LICENSE.txt
axioms_flask_py-0.0.20.dist-info/METADATA
axioms_flask_py-0.0.20.dist-info/WHEEL
axioms_flask_py-0.0.20.dist-info/top_level.txt
axioms_flask_py-0.0.20.dist-info/RECORD
