Metadata-Version: 2.4
Name: axioms-flask-py
Version: 0.0.20
Summary: OAuth2/OIDC authentication and authorization for Flask APIs. Supports authentication and claim-based fine-grained authorization (scopes, roles, permissions) using JWT tokens.
Author-email: Abhishek Tiwari <abhishek@abhishek-tiwari.com>
License: MIT
Project-URL: Homepage, https://github.com/abhishektiwari/axioms-flask-py
Project-URL: Documentation, https://axioms-flask-py.abhishek-tiwari.com/
Project-URL: Source, https://github.com/abhishektiwari/axioms-flask-py
Project-URL: Tracker, https://github.com/abhishektiwari/axioms-flask-py/issues
Project-URL: Changelog, https://github.com/abhishektiwari/axioms-flask-py/releases
Keywords: axioms,authentication,authorization,iam,authz,authn,jwt,openid,oauth2
Classifier: Development Status :: 5 - Production/Stable
Classifier: License :: OSI Approved :: MIT License
Classifier: Operating System :: OS Independent
Classifier: Intended Audience :: Developers
Classifier: Topic :: Internet :: WWW/HTTP
Classifier: Topic :: Security
Classifier: Topic :: Software Development :: Libraries :: Python Modules
Classifier: Topic :: System :: Systems Administration :: Authentication/Directory
Classifier: Framework :: Flask
Classifier: Programming Language :: Python :: 3
Classifier: Programming Language :: Python :: 3.7
Classifier: Programming Language :: Python :: 3.8
Classifier: Programming Language :: Python :: 3.9
Classifier: Programming Language :: Python :: 3.10
Classifier: Programming Language :: Python :: 3.11
Classifier: Programming Language :: Python :: 3.12
Classifier: Programming Language :: Python :: 3.13
Requires-Python: >=3.7
License-File: LICENSE.txt
Requires-Dist: pyjwt
Requires-Dist: jwcrypto
Requires-Dist: python-box
Requires-Dist: Flask
Requires-Dist: Flask-DotEnv
Provides-Extra: dev
Requires-Dist: black>=23.0.0; extra == "dev"
Requires-Dist: ruff>=0.1.0; extra == "dev"
Requires-Dist: pytest>=7.0.0; extra == "dev"
Requires-Dist: pytest-cov>=4.0.0; extra == "dev"
Requires-Dist: build>=1.0.0; extra == "dev"
Requires-Dist: twine>=4.0.0; extra == "dev"
Requires-Dist: sphinx>=7.0.0; extra == "dev"
Requires-Dist: sphinx-book-theme>=1.0.0; extra == "dev"
Requires-Dist: sphinx-autobuild>=2021.3.14; extra == "dev"
Requires-Dist: sphinx-copybutton>=0.5.0; extra == "dev"
Dynamic: license-file
